pygeoinf/__init__.py
pygeoinf/auxiliary.py
pygeoinf/backus_gilbert.py
pygeoinf/checks/__init__.py
pygeoinf/checks/hilbert_space.py
pygeoinf/checks/linear_operators.py
pygeoinf/checks/nonlinear_operators.py
pygeoinf/direct_sum.py
pygeoinf/forward_problem.py
pygeoinf/gaussian_measure.py
pygeoinf/hilbert_space.py
pygeoinf/inversion.py
pygeoinf/linear_bayesian.py
pygeoinf/linear_forms.py
pygeoinf/linear_operators.py
pygeoinf/linear_optimisation.py
pygeoinf/linear_solvers.py
pygeoinf/nonlinear_forms.py
pygeoinf/nonlinear_operators.py
pygeoinf/nonlinear_optimisation.py
pygeoinf/parallel.py
pygeoinf/plot.py
pygeoinf/preconditioners.py
pygeoinf/random_matrix.py
pygeoinf/subsets.py
pygeoinf/subspaces.py
pygeoinf/symmetric_space/__init__.py
pygeoinf/symmetric_space/circle.py
pygeoinf/symmetric_space/sh_tools.py
pygeoinf/symmetric_space/sphere.py
pygeoinf/symmetric_space/symmetric_space.py
pygeoinf/utils.py
pygeoinf-1.3.9.dist-info/METADATA
pygeoinf-1.3.9.dist-info/WHEEL
pygeoinf-1.3.9.dist-info/licenses/LICENSE
pygeoinf-1.3.9.dist-info/RECORD
