Metadata-Version: 2.4
Name: pygeoinf
Version: 1.3.9
Summary: A package for solving geophysical inference and inverse problems
License: BSD-3-Clause
License-File: LICENSE
Author: David Al-Attar and Dan Heathcote
Requires-Python: >=3.11
Classifier: License :: OSI Approved :: BSD License
Classifier: Programming Language :: Python :: 3
Classifier: Programming Language :: Python :: 3.11
Classifier: Programming Language :: Python :: 3.12
Classifier: Programming Language :: Python :: 3.13
Classifier: Programming Language :: Python :: 3.14
Provides-Extra: sphere
Requires-Dist: Cartopy (>=0.23.0,<0.24.0) ; extra == "sphere"
Requires-Dist: joblib (>=1.5.2,<2.0.0)
Requires-Dist: matplotlib (>=3.0.0)
Requires-Dist: numpy (>=1.26.0)
Requires-Dist: pyqt6 (>=6.0.0)
Requires-Dist: pyshtools (>=4.0.0) ; extra == "sphere"
Requires-Dist: scipy (>=1.16.1)
Requires-Dist: threadpoolctl (>=3.6.0,<4.0.0)
